httptrading/__init__.py
httptrading/http_server.py
httptrading/model.py
httptrading/broker/__init__.py
httptrading/broker/base.py
httptrading/broker/futu_sec.py
httptrading/broker/interactive_brokers.py
httptrading/broker/longbridge.py
httptrading/broker/moomoo_sec.py
httptrading/broker/tiger.py
httptrading/tool/__init__.py
httptrading/tool/leaky_bucket.py
httptrading/tool/locate.py
httptrading/tool/time.py
httptrading-1.0.8.dist-info/licenses/LICENSE
httptrading-1.0.8.dist-info/METADATA
httptrading-1.0.8.dist-info/WHEEL
httptrading-1.0.8.dist-info/top_level.txt
httptrading-1.0.8.dist-info/RECORD
