Metadata-Version: 2.4
Name: httptrading
Version: 1.0.8
Summary: 统一交易通道的接口服务
Author-email: songwei <github@songwei.name>
License: MIT
Requires-Python: >=3.13
License-File: LICENSE
Requires-Dist: aiohttp>=3.12.6
Requires-Dist: humanize>=4.12.3
Requires-Dist: tomlkit>=0.13.2
Requires-Dist: nest-asyncio>=1.6.0
Dynamic: license-file
